Metadata-Version: 2.1
Name: odoo13-addon-stock-picking-group-by-partner-by-carrier
Version: 13.0.1.10.2
Summary: Stock Picking: group by partner and carrier
Home-page: https://github.com/OCA/stock-logistics-workflow
Author: Camptocamp, BCIM, Odoo Community Association (OCA)
Author-email: support@odoo-community.org
License: AGPL-3
Platform: UNKNOWN
Classifier: Programming Language :: Python
Classifier: Framework :: Odoo
Classifier: Framework :: Odoo :: 13.0
Classifier: License :: OSI Approved :: GNU Affero General Public License v3
Classifier: Development Status :: 3 - Alpha
Requires-Python: >=3.5
Requires-Dist: odoo13-addon-stock-move-assign-picking-hook
Requires-Dist: odoo (<13.1dev,>=13.0a)
